easyaccess/__init__.py
easyaccess/config_ea.py
easyaccess/eaparser.py
easyaccess/easyaccess.py
easyaccess/version.py
easyaccess/eautils/__init__.py
easyaccess/eautils/cli_utils.py
easyaccess/eautils/db_api.py
easyaccess/eautils/db_utils.py
easyaccess/eautils/des_logo.py
easyaccess/eautils/des_utils.py
easyaccess/eautils/dircache.py
easyaccess/eautils/dtypes.py
easyaccess/eautils/ea_utils.py
easyaccess/eautils/fileio.py
easyaccess/eautils/fun_utils.py
easyaccess/eautils/import_utils.py
easyaccess/eautils/python_api.py
easyaccess-1.4.12.data/scripts/easyaccess
easyaccess-1.4.12.dist-info/AUTHORS.md
easyaccess-1.4.12.dist-info/LICENSE.txt
easyaccess-1.4.12.dist-info/METADATA
easyaccess-1.4.12.dist-info/WHEEL
easyaccess-1.4.12.dist-info/top_level.txt
easyaccess-1.4.12.dist-info/RECORD
