Metadata-Version: 2.1
Name: easyaccess
Version: 1.4.12
Summary: Easy access to the DES DB. Enhanced command line SQL interpreter client for DES
Home-page: https://github.com/des-labs/easyaccess
Author: Matias Carrasco Kind
Author-email: mcarras2@illinois.edu
License: LICENSE.txt
License-File: LICENSE.txt
License-File: AUTHORS.md
Requires-Dist: pandas (>=0.14)
Requires-Dist: termcolor
Requires-Dist: fitsio (==1.1.8)
Requires-Dist: cx-Oracle (==8.0.1)
Requires-Dist: numpy (>=1.19.2)
Requires-Dist: future (>=0.15.0)
Requires-Dist: requests
Requires-Dist: setuptools
